skplatform/__init__.py
skplatform/_version.py
skplatform/geodesy.py
skplatform/solar.py
skplatform/celestialbodies/__init__.py
skplatform/celestialbodies/celestialbody.py
skplatform/devs/ali_atmosphere_curtain.py
skplatform/devs/technique_orbital_angle.py
skplatform/orientation_techniques/__init__.py
skplatform/orientation_techniques/orientation_techniques_core.py
skplatform/orientation_techniques/standard_orientation_techniques.py
skplatform/platform/__init__.py
skplatform/platform/optical_geometry.py
skplatform/platform/platform.py
skplatform/platform/platform_pointing.py
skplatform/platform/platformlocator.py
skplatform/platform/positionandorientationarray.py
skplatform/platform/rotationmatrix.py
skplatform/satellite/__init__.py
skplatform/satellite/coe.py
skplatform/satellite/gibbs.py
skplatform/satellite/satellite_simplegeostationary.py
skplatform/satellite/satellitebase.py
skplatform/satellite/satellitekepler.py
skplatform/satellite/satellitemolniya.py
skplatform/satellite/satellitesgp4.py
skplatform/satellite/satellitesunsync.py
skplatform/satellite/satellitetudat.py
skplatform/scripting/.gitignore
skplatform/scripting/README.md
skplatform/scripting/__init__.py
skplatform/scripting/cli.py
skplatform/scripting/conversion.py
skplatform/scripting/instruments.py
skplatform/scripting/interface.py
skplatform/scripting/propagator.py
skplatform/scripting/rotations.py
skplatform/scripting/tests.py
skplatform/scripting/examples/AOS_Storm_Inclined_v2025-01-29_Epoch2019.tle
skplatform/scripting/examples/interface_example.py
skplatform/scripting/examples/plotting_example.py
skplatform/scripting/examples/output/.gitignore
skplatform/scripting/tests/__init__.py
skplatform/scripting/tests/angles.png
skplatform/scripting/tests/angles.py
skplatform/scripting/tests/generate_orbit_test_data.py
skplatform/scripting/tests/orbit_test_data.py
skplatform/scripting/tests/test_orbits.py
skplatform/scripting/tests/test_propagators.py
skplatform/scripting/tests/test_rotations.py
skplatform-0.2.17.dist-info/licenses/LICENSE
skplatform-0.2.17.dist-info/METADATA
skplatform-0.2.17.dist-info/WHEEL
skplatform-0.2.17.dist-info/top_level.txt
skplatform-0.2.17.dist-info/RECORD
