Metadata-Version: 2.4
Name: skplatform
Version: 0.2.17
Summary: Attitude solutions for optical, remote sensing instruments  flying on, or simulating, balloons, aircraft and satellites
Author-email: Nick Lloyd <nick.lloyd@usask.ca>
License: MIT
Classifier: Development Status :: 4 - Beta
Classifier: License :: OSI Approved :: MIT License
Classifier: Programming Language :: Python :: 3 :: Only
Classifier: Programming Language :: Python :: 3.7
Classifier: Programming Language :: Python :: 3.8
Classifier: Programming Language :: Python :: 3.9
Classifier: Programming Language :: Python :: 3.10
Classifier: Programming Language :: Python :: 3.11
Classifier: Programming Language :: Python :: 3.12
Classifier: Programming Language :: Python :: 3.13
Requires-Python: >=3.7
License-File: LICENSE
Requires-Dist: numpy
Requires-Dist: sktimeutils>=2.0.9
Requires-Dist: skconfig>=0.3.5
Requires-Dist: sgp4>=2.9
Requires-Dist: jplephem
Requires-Dist: astropy
Requires-Dist: xarray
Dynamic: license-file
